{
    "id": "leyl-suresi",
    "name": "The Night",
    "description": "The Night - 92",
    "index": 92,
    "sentences": [
        {
            "id": "1",
            "sentence": " وَٱلَّيْلِ إِذَا يَغْشَىٰ",
            "translation": "By the night when it covers,",
            "originals": [
                "وَٱلَّيْلِ",
                "إِذَا",
                "يَغْشَىٰ"
            ],
            "translations": [
                "By the night",
                "when",
                "it covers"
            ]
        },
        {
            "id": "2",
            "sentence": "وَٱلنَّهَارِ إِذَا تَجَلَّىٰ",
            "translation": "and the day when it shines!",
            "originals": [
                "وَٱلنَّهَارِ",
                "إِذَا",
                "تَجَلَّىٰ"
            ],
            "translations": [
                "And the day",
                "when",
                "it shines in brightness"
            ]
        },
        {
            "id": "3",
            "sentence": "وَمَا خَلَقَ ٱلذَّكَرَ وَٱلْأُنثَىٰٓ",
            "translation": "And by ˹the One˺ Who created male and female!",
            "originals": [
                "وَمَا",
                "خَلَقَ",
                "ٱلذَّكَرَ",
                "وَٱلْأُنثَىٰٓ"
            ],
            "translations": [
                "And He Who",
                "created",
                "the male",
                "and the female"
            ]
        },
        {
            "id": "4",
            "sentence": "إِنَّ سَعْيَكُمْ لَشَتَّىٰ",
            "translation": "Surely the ends you strive for are diverse.",
            "originals": [
                "إِنَّ",
                "سَعْيَكُمْ",
                "لَشَتَّىٰ"
            ],
            "translations": [
                "Indeed",
                "your efforts",
                "(are) surely diverse"
            ]
        },
        {
            "id": "5",
            "sentence": "فَأَمَّا مَنْ أَعْطَىٰ وَٱتَّقَىٰ",
            "translation": "As for the one who is charitable, mindful ˹of Allah˺,",
            "originals": [
                "فَأَمَّا",
                "مَنْ",
                "أَعْطَىٰ",
                "وَٱتَّقَىٰ"
            ],
            "translations": [
                "Then as for",
                "(him) who",
                "gives",
                "and fears"
            ]
        },
        {
            "id": "6",
            "sentence": "وَصَدَّقَ بِٱلْحُسْنَىٰ",
            "translation": "and ˹firmly˺ believes in the finest reward,",
            "originals": [
                "وَصَدَّقَ",
                "بِٱلْحُسْنَىٰ"
            ],
            "translations": [
                "And believes",
                "in the best"
            ]
        },
        {
            "id": "7",
            "sentence": "فَسَنُيَسِّرُهُۥ لِلْيُسْرَىٰ",
            "translation": "We will facilitate for them the Way of Ease.",
            "originals": [
                "فَسَنُيَسِّرُهُۥ",
                "لِلْيُسْرَىٰ"
            ],
            "translations": [
                "Then We will ease him",
                "towards [the] ease"
            ]
        },
        {
            "id": "8",
            "sentence": "وَأَمَّا مَنۢ بَخِلَ وَٱسْتَغْنَىٰ",
            "translation": "And as for the one who is stingy, indifferent ˹to Allah˺,",
            "originals": [
                "وَأَمَّا",
                "مَنۢ",
                "بَخِلَ",
                "وَٱسْتَغْنَىٰ"
            ],
            "translations": [
                "But as for",
                "(him) who",
                "withholds",
                "and considers himself free from need"
            ]
        },
        {
            "id": "9",
            "sentence": "وَكَذَّبَ بِٱلْحُسْنَىٰ",
            "translation": "and ˹staunchly˺ denies the finest reward,",
            "originals": [
                "وَكَذَّبَ",
                "بِٱلْحُسْنَىٰ"
            ],
            "translations": [
                "And denies",
                "the best"
            ]
        },
        {
            "id": "10",
            "sentence": "فَسَنُيَسِّرُهُۥ لِلْعُسْرَىٰ",
            "translation": "We will facilitate for them the path of hardship.",
            "originals": [
                "فَسَنُيَسِّرُهُۥ",
                "لِلْعُسْرَىٰ"
            ],
            "translations": [
                "Then We will ease him",
                "towards [the] difficulty"
            ]
        },
        {
            "id": "11",
            "sentence": "وَمَا يُغْنِى عَنْهُ مَالُهُۥٓ إِذَا تَرَدَّىٰٓ",
            "translation": "And their wealth will be of no benefit to them when they tumble ˹into Hell˺.",
            "originals": [
                "وَمَا",
                "يُغْنِى",
                "عَنْهُ",
                "مَالُهُۥٓ",
                "إِذَا",
                "تَرَدَّىٰٓ"
            ],
            "translations": [
                "And not",
                "will avail",
                "him",
                "his wealth",
                "when",
                "he falls"
            ]
        },
        {
            "id": "12",
            "sentence": "إِنَّ عَلَيْنَا لَلْهُدَىٰ",
            "translation": "It is certainly upon Us ˹alone˺ to show ˹the way to˺ guidance.",
            "originals": [
                "إِنَّ",
                "عَلَيْنَا",
                "لَلْهُدَىٰ"
            ],
            "translations": [
                "Indeed",
                "upon Us",
                "(is) the guidance"
            ]
        },
        {
            "id": "13",
            "sentence": "وَإِنَّ لَنَا لَلْـَٔاخِرَةَ وَٱلْأُولَىٰ",
            "translation": "And surely to Us ˹alone˺ belong this life and the next.",
            "originals": [
                "وَإِنَّ",
                "لَنَا",
                "لَلْـَٔاخِرَةَ",
                "وَٱلْأُولَىٰ"
            ],
            "translations": [
                "And indeed",
                "for Us",
                "(is) the Hereafter",
                "and the first (life)"
            ]
        },
        {
            "id": "14",
            "sentence": "فَأَنذَرْتُكُمْ نَارًا تَلَظَّىٰ",
            "translation": "And so I have warned you of a raging Fire,",
            "originals": [
                "فَأَنذَرْتُكُمْ",
                "نَارًۭا",
                "تَلَظَّىٰ"
            ],
            "translations": [
                "So I warn you",
                "(of) a Fire",
                "blazing"
            ]
        }
    ]
}