{
    "id": "tarik-suresi",
    "name": "Tarik Suresi",
    "description": "Tarik Suresi - 86. sure",
    "index": 86,
    "sentences": [
        {
            "id": "1",
            "sentence": "وَالسَّمَٓاءِ وَالطَّارِقِۙ",
            "translation": "Yemîn olsun o göğe ve Târık'a!",
            "originals": [
                "وَالسَّمَٓاءِ",
                "وَالطَّارِقِۙ"
            ],
            "translations": [
                "göğe andolsun",
                "ve tarık`a"
            ]
        },
        {
            "id": "2",
            "sentence": "وَمَٓا اَدْرٰيكَ مَا الطَّارِقُۙ",
            "translation": "Târık'ın ne olduğunu sana ne bildirdi?",
            "originals": [
                "وَمَٓا اَدْرٰيكَ",
                "مَا",
                "الطَّارِقُۙ"
            ],
            "translations": [
                "sen nereden bileceksin?",
                "nedir",
                "tarık"
            ]
        },
        {
            "id": "3",
            "sentence": "اَلنَّجْمُ الثَّاقِبُۙ",
            "translation": "O, (nûruyla karanlığı) delen yıldızdır.",
            "originals": [
                "اَلنَّجْمُ",
                "الثَّاقِبُۙ"
            ],
            "translations": [
                "yıldızdır",
                "parlayan"
            ]
        },
        {
            "id": "4",
            "sentence": "اِنْ كُلُّ نَفْسٍ لَمَّا عَلَيْهَا حَافِظٌۜ",
            "translation": "Hiçbir nefis yoktur ki, üzerinde bir gözetici (koruyucu melek) bulunmasın!",
            "originals": [
                "اِنْ كُلُّ نَفْسٍ",
                "لَمَّا",
                "عَلَيْهَا",
                "حَافِظٌۜ"
            ],
            "translations": [
                "hiçbir can yoktur ki",
                "olmasın",
                "başında",
                "bir koruyucu"
            ]
        },
        {
            "id": "5",
            "sentence": "فَلْيَنْظُرِ الْاِنْسَانُ مِمَّ خُلِقَۜ",
            "translation": "O hâlde insan, neden yaratıldığına bir baksın!",
            "originals": [
                "فَلْيَنْظُرِ",
                "الْاِنْسَانُ",
                "مِمَّ",
                "خُلِقَۜ"
            ],
            "translations": [
                "bir baksın",
                "insan",
                "neden",
                "yaratıldığına"
            ]
        },
        {
            "id": "6",
            "sentence": "خُلِقَ مِنْ مَٓاءٍ دَافِقٍۙ",
            "translation": "(O) atılan bir sudan yaratıldı.",
            "originals": [
                "خُلِقَ",
                "مِنْ مَٓاءٍ",
                "دَافِقٍۙ"
            ],
            "translations": [
                "yaratıldı",
                "bir sudan",
                "atılan"
            ]
        },
        {
            "id": "7",
            "sentence": "يَخْرُجُ مِنْ بَيْنِ الصُّلْبِ وَالتَّرَٓائِبِۜ",
            "translation": "(Bu su) bel kemiği ile göğüs kemikleri arasın(daki uzuvlar)dan çıkar.",
            "originals": [
                "يَخْرُجُ",
                "مِنْ بَيْنِ",
                "الصُّلْبِ",
                "وَالتَّرَٓائِبِۜ"
            ],
            "translations": [
                "çıkan",
                "arasından",
                "bel",
                "ve kaburga kemikleri"
            ]
        },
        {
            "id": "8",
            "sentence": "اِنَّهُ عَلٰى رَجْعِه۪ لَقَادِرٌۜ",
            "translation": "Şübhesiz ki O (Allah), onu geri döndürmeğe (öldürdükten sonra tekrar diriltmeğe)elbette gücü yetendir.",
            "originals": [
                "اِنَّهُ",
                "عَلٰى رَجْعِه۪",
                "لَقَادِرٌۜ"
            ],
            "translations": [
                "şüphesiz O",
                "onu tekrar döndürmeye",
                "kadirdir"
            ]
        },
        {
            "id": "9",
            "sentence": "يَوْمَ تُبْلَى السَّرَٓائِرُۙ",
            "translation": "O gün (kalblerde bulunan) sırlar ortaya çıkarılır.",
            "originals": [
                "يَوْمَ",
                "تُبْلَى",
                "السَّرَٓائِرُۙ"
            ],
            "translations": [
                "gün",
                "yoklanacağı",
                "sırların"
            ]
        },
        {
            "id": "10",
            "sentence": "فَمَا لَهُ مِنْ قُوَّةٍ وَلَا نَاصِرٍۜ",
            "translation": "Artık o (insan) için ne bir kuvvet vardır, ne de bir yardımcı!",
            "originals": [
                "فَمَا",
                "لَهُ",
                "مِنْ قُوَّةٍ",
                "وَلَا",
                "نَاصِرٍۜ"
            ],
            "translations": [
                "yoktur",
                "onun",
                "bir gücü",
                "ne de",
                "bir yardımcısı"
            ]
        },
        {
            "id": "11",
            "sentence": "وَالسَّمَٓاءِ ذَاتِ الرَّجْعِۙ",
            "translation": "Yemîn olsun o dönüşlü (hâlden hâle giren) göğe!",
            "originals": [
                "وَالسَّمَٓاءِ",
                "ذَاتِ الرَّجْعِۙ"
            ],
            "translations": [
                "göğe andolsun",
                "dönüşlü"
            ]
        },
        {
            "id": "12",
            "sentence": "وَالْاَرْضِ ذَاتِ الصَّدْعِۙ",
            "translation": "O (bitkilerle, vâdilerle yarılarak) yarıklar sâhibi olan yeryüzüne!",
            "originals": [
                "وَالْاَرْضِ",
                "ذَاتِ الصَّدْعِۙ"
            ],
            "translations": [
                "ve yere andolsun",
                "çatlayan"
            ]
        },
        {
            "id": "13",
            "sentence": "اِنَّهُ لَقَوْلٌ فَصْلٌۙ",
            "translation": "13,14. Şübhesiz ki o (Kur'ân), elbet (hak ile bâtılı) ayıran bir sözdür. Ve o, şaka değildir!",
            "originals": [
                "اِنَّهُ",
                "لَقَوْلٌ",
                "فَصْلٌۙ"
            ],
            "translations": [
                "O",
                "elbette bir sözdür",
                "ayırdedici"
            ]
        },
        {
            "id": "14",
            "sentence": "وَمَا هُوَ بِالْهَزْلِۜ",
            "translation": "13,14. Şübhesiz ki o (Kur'ân), elbet (hak ile bâtılı) ayıran bir sözdür. Ve o, şaka değildir!",
            "originals": [
                "وَمَا",
                "هُوَ",
                "بِالْهَزْلِۜ"
            ],
            "translations": [
                "ve değildir",
                "O",
                "şaka"
            ]
        },
        {
            "id": "15",
            "sentence": "اِنَّهُمْ يَك۪يدُونَ كَيْداًۙ",
            "translation": "15,16. Gerçekten onlar, (Kur'ân'ı ibtâl etmek için) bir hîle olarak tuzak kuruyorlar.(Ben de) bir hîle ile (kurdukları) tuzak(larını ibtâl) ederim!",
            "originals": [
                "اِنَّهُمْ",
                "يَك۪يدُونَ",
                "كَيْداًۙ"
            ],
            "translations": [
                "onlar",
                "kuruyorlar",
                "bir tuzak"
            ]
        },
        {
            "id": "16",
            "sentence": "وَاَ‌ك۪يدُ كَيْداًۚ",
            "translation": "15,16. Gerçekten onlar, (Kur'ân'ı ibtâl etmek için) bir hîle olarak tuzak kuruyorlar.(Ben de) bir hîle ile (kurdukları) tuzak(larını ibtâl) ederim!",
            "originals": [
                "وَاَ‌ك۪يدُ",
                "كَيْداًۚ"
            ],
            "translations": [
                "ben de kuruyorum",
                "bir tuzak"
            ]
        },
        {
            "id": "17",
            "sentence": "فَمَهِّلِ الْـكَافِر۪ينَ اَمْهِلْهُمْ رُوَيْداً",
            "translation": "(Ey Habîbim!) O hâlde kâfirlere (azâb edeceğimiz vakte kadar) mühlet ver; onlara azıcık süre tanımakla, biraz (kendi hâllerine) bırak!",
            "originals": [
                "فَمَهِّلِ",
                "الْـكَافِر۪ينَ",
                "اَمْهِلْهُمْ",
                "رُوَيْداً"
            ],
            "translations": [
                "sen mühlet ver",
                "kafirlere",
                "bırak onları",
                "kendi hallerine"
            ]
        }
    ]
}